test_django_cookie_app/__init__.py
test_django_cookie_app/apps.py
test_django_cookie_app/models.py
test_django_cookie_app/urls.py
test_django_cookie_app/views.py
test_django_cookie_app/static/css/test_django_cookie_app.css
test_django_cookie_app/static/js/test_django_cookie_app.js
test_django_cookie_app/templates/test_django_cookie_app/base.html
test_django_cookie_app-0.1.0.dist-info/AUTHORS.rst
test_django_cookie_app-0.1.0.dist-info/LICENSE
test_django_cookie_app-0.1.0.dist-info/METADATA
test_django_cookie_app-0.1.0.dist-info/WHEEL
test_django_cookie_app-0.1.0.dist-info/top_level.txt
test_django_cookie_app-0.1.0.dist-info/RECORD
