Metadata-Version: 2.1
Name: test-django-cookie-app
Version: 0.1.0
Summary: Learning DjangoCookieCuttterApp
Home-page: https://github.com/greatbharat/test_django_cookie_app
Author: Bharat G. Gaikwad
Author-email: greatbharatin8@gmail.com
License: MIT
Keywords: test_django_cookie_app
Platform: UNKNOWN
Classifier: Development Status :: 3 - Alpha
Classifier: Framework :: Django :: 2.0
Classifier: Intended Audience :: Developers
Classifier: License :: OSI Approved :: BSD License
Classifier: Natural Language :: English
Classifier: Programming Language :: Python :: 2
Classifier: Programming Language :: Python :: 2.7
Classifier: Programming Language :: Python :: 3
Classifier: Programming Language :: Python :: 3.4
Classifier: Programming Language :: Python :: 3.5
Classifier: Programming Language :: Python :: 3.6
Requires-Dist: django-model-utils (>=2.0)
